kubipy/__init__.py
kubipy/utils.py
kubipy-0.1.9.5.dist-info/LICENSE
kubipy-0.1.9.5.dist-info/METADATA
kubipy-0.1.9.5.dist-info/WHEEL
kubipy-0.1.9.5.dist-info/top_level.txt
kubipy-0.1.9.5.dist-info/RECORD
