Metadata-Version: 2.1
Name: kubipy
Version: 0.1.9.5
Summary: Python interface for Minikube
Home-page: https://github.com/LJStroemsdoerfer/kubipy
Author: Lukas Jan Stroemsdoerfer
Author-email: ljstroemsdoerfer@gmail.com
License: MIT
Platform: UNKNOWN
